MDOFModel/Alpha_CNcode.py
MDOFModel/BldLossAssessment.py
MDOFModel/IDA.py
MDOFModel/MDOFOpenSees.py
MDOFModel/MDOF_CN.py
MDOFModel/MDOF_LU.py
MDOFModel/ReadRecord.py
MDOFModel/Tool_IDA.py
MDOFModel/Tool_LossAssess.py
MDOFModel/__init__.py
MDOFModel/Resources/China_Mainland_SCK_Vs30.xlsx
MDOFModel/Resources/GB50011-2010(2016)-Appendix-A.csv
MDOFModel/Resources/GB50011-2010(2016)-Table 5.5.5.csv
MDOFModel/Resources/HazusData Table 15.2.csv
MDOFModel/Resources/HazusData Table 15.3.csv
MDOFModel/Resources/HazusData Table 15.4.csv
MDOFModel/Resources/HazusData Table 15.5.csv
MDOFModel/Resources/HazusData Table 5.1.csv
MDOFModel/Resources/HazusData Table 5.10.csv
MDOFModel/Resources/HazusData Table 5.12.csv
MDOFModel/Resources/HazusData Table 5.18.csv
MDOFModel/Resources/HazusData Table 5.4.csv
MDOFModel/Resources/HazusData Table 5.5.csv
MDOFModel/Resources/HazusData Table 5.6.csv
MDOFModel/Resources/HazusData Table 5.9.csv
MDOFModel/Resources/HazusData4-2 Table 11-7.csv
MDOFModel/Resources/HazusData4-2 Table 11-8.csv
MDOFModel/Resources/HazusData4-2 Table 11-9.csv
MDOFModel/Resources/HazusInventory Table 4-2.csv
MDOFModel/Resources/HazusInventory Table 6-2.csv
MDOFModel/Resources/HazusInventory Table 6-3.csv
MDOFModel/Resources/HazusInventory Table 6-9.csv
MDOFModel/Resources/Readme.txt
MDOFModel/Resources/FEMA_P-695_far-field_ground_motions/MetaData.txt
MDOFModel/Resources/FEMA_P-695_far-field_ground_motions/MetaData_part10.txt
MDOFModel/Resources/FEMA_P-695_far-field_ground_motions/NGA_no_829_RIO270.txt
MDOFModel/Resources/FEMA_P-695_far-field_ground_motions/NGA_no_829_RIO360.txt
MDOFModel/Resources/FEMA_P-695_far-field_ground_motions/RSN1111_KOBE_NIS000.txt
MDOFModel/Resources/FEMA_P-695_far-field_ground_motions/RSN1111_KOBE_NIS090.txt
MDOFModel/Resources/FEMA_P-695_far-field_ground_motions/RSN1116_KOBE_SHI000.txt
MDOFModel/Resources/FEMA_P-695_far-field_ground_motions/RSN1116_KOBE_SHI090.txt
mdofmodel-0.1.1.dist-info/METADATA
mdofmodel-0.1.1.dist-info/WHEEL
mdofmodel-0.1.1.dist-info/licenses/LICENSE
mdofmodel-0.1.1.dist-info/RECORD
