Metadata-Version: 2.4
Name: MDOFModel
Version: 0.1.1
Summary: Generate MDOF lumped mass FE model using basic building information
Project-URL: Homepage, https://github.com/youtian95/MDOFModel
Project-URL: Bug Tracker, https://github.com/youtian95/MDOFModel/issues
Author-email: Tian You <youtian@njtech.edu.cn>
License-File: LICENSE
Classifier: License :: OSI Approved :: GNU General Public License v3 (GPLv3)
Classifier: Operating System :: OS Independent
Classifier: Programming Language :: Python :: 3
Requires-Python: >=3.12
Requires-Dist: eqsig
Requires-Dist: matplotlib
Requires-Dist: numpy
Requires-Dist: openpyxl
Requires-Dist: openseespy
Requires-Dist: pandas
